<?xml version="1.0" encoding="UTF-8"?>
<list xmlns:xsi="http://www.w3.org/2001/XMLSchema-instance" xsi:noNamespaceSchemaLocation="../../xsd/items.xsd">
	<item id="26000" name="+5 Apocalypse Retributer Pack" type="EtcItem">
		<!-- Double-click to obtain the item as described in the pack name. -->
		<set name="icon" val="icon.etc_treasure_box_i08" />
		<set name="is_sellable" val="false" />
		<set name="is_stackable" val="true" />
		<set name="default_action" val="CAPSULE" />
		<set name="material" val="PAPER" />
		<set name="handler" val="ItemSkills" />
		<skills>
			<skill id="27123" level="1" /> <!-- +5 Apocalypse Retributer Pack -->
		</skills>
	</item>
	<item id="26001" name="+6 Apocalypse Retributer Pack" type="EtcItem">
		<!-- Double-click to obtain the item as described in the pack name. -->
		<set name="icon" val="icon.etc_treasure_box_i08" />
		<set name="is_sellable" val="false" />
		<set name="is_stackable" val="true" />
		<set name="default_action" val="CAPSULE" />
		<set name="material" val="PAPER" />
		<set name="handler" val="ItemSkills" />
		<skills>
			<skill id="27124" level="1" /> <!-- +6 Apocalypse Retributer Pack -->
		</skills>
	</item>
	<item id="26002" name="+7 Apocalypse Retributer Pack" type="EtcItem">
		<!-- Double-click to obtain the item as described in the pack name. -->
		<set name="icon" val="icon.etc_treasure_box_i08" />
		<set name="is_sellable" val="false" />
		<set name="is_stackable" val="true" />
		<set name="default_action" val="CAPSULE" />
		<set name="material" val="PAPER" />
		<set name="handler" val="ItemSkills" />
		<skills>
			<skill id="27125" level="1" /> <!-- +7 Apocalypse Retributer Pack -->
		</skills>
	</item>
	<item id="26003" name="+8 Apocalypse Retributer Pack" type="EtcItem">
		<!-- Double-click to obtain the item as described in the pack name. -->
		<set name="icon" val="icon.etc_treasure_box_i08" />
		<set name="is_sellable" val="false" />
		<set name="is_stackable" val="true" />
		<set name="default_action" val="CAPSULE" />
		<set name="material" val="PAPER" />
		<set name="handler" val="ItemSkills" />
		<skills>
			<skill id="27126" level="1" /> <!-- +8 Apocalypse Retributer Pack -->
		</skills>
	</item>
	<item id="26004" name="+9 Apocalypse Retributer Pack" type="EtcItem">
		<!-- Double-click to obtain the item as described in the pack name. -->
		<set name="icon" val="icon.etc_treasure_box_i08" />
		<set name="is_sellable" val="false" />
		<set name="is_stackable" val="true" />
		<set name="default_action" val="CAPSULE" />
		<set name="material" val="PAPER" />
		<set name="handler" val="ItemSkills" />
		<skills>
			<skill id="27127" level="1" /> <!-- +9 Apocalypse Retributer Pack -->
		</skills>
	</item>
	<item id="26005" name="+10 Apocalypse Retributer Pack" type="EtcItem">
		<!-- Double-click to obtain the item as described in the pack name. -->
		<set name="icon" val="icon.etc_treasure_box_i08" />
		<set name="is_sellable" val="false" />
		<set name="is_stackable" val="true" />
		<set name="default_action" val="CAPSULE" />
		<set name="material" val="PAPER" />
		<set name="handler" val="ItemSkills" />
		<skills>
			<skill id="27128" level="1" /> <!-- +10 Apocalypse Retributer Pack -->
		</skills>
	</item>
	<item id="26006" name="+4 Apocalypse Dual Sword Pack" type="EtcItem">
		<!-- Double-click to obtain the item as described in the pack name. -->
		<set name="icon" val="icon.etc_treasure_box_i08" />
		<set name="is_sellable" val="false" />
		<set name="is_stackable" val="true" />
		<set name="default_action" val="CAPSULE" />
		<set name="material" val="PAPER" />
		<set name="handler" val="ItemSkills" />
		<skills>
			<skill id="27129" level="1" /> <!-- +4 Apocalypse Dual Sword Pack -->
		</skills>
	</item>
	<item id="26007" name="+5 Apocalypse Dual Sword Pack" type="EtcItem">
		<!-- Double-click to obtain the item as described in the pack name. -->
		<set name="icon" val="icon.etc_treasure_box_i08" />
		<set name="is_sellable" val="false" />
		<set name="is_stackable" val="true" />
		<set name="default_action" val="CAPSULE" />
		<set name="material" val="PAPER" />
		<set name="handler" val="ItemSkills" />
		<skills>
			<skill id="27130" level="1" /> <!-- +5 Apocalypse Dual Sword Pack -->
		</skills>
	</item>
	<item id="26008" name="+6 Apocalypse Dual Sword Pack" type="EtcItem">
		<!-- Double-click to obtain the item as described in the pack name. -->
		<set name="icon" val="icon.etc_treasure_box_i08" />
		<set name="is_sellable" val="false" />
		<set name="is_stackable" val="true" />
		<set name="default_action" val="CAPSULE" />
		<set name="material" val="PAPER" />
		<set name="handler" val="ItemSkills" />
		<skills>
			<skill id="27131" level="1" /> <!-- +6 Apocalypse Dual Sword Pack -->
		</skills>
	</item>
	<item id="26009" name="+7 Apocalypse Dual Sword Pack" type="EtcItem">
		<!-- Double-click to obtain the item as described in the pack name. -->
		<set name="icon" val="icon.etc_treasure_box_i08" />
		<set name="is_sellable" val="false" />
		<set name="is_stackable" val="true" />
		<set name="default_action" val="CAPSULE" />
		<set name="material" val="PAPER" />
		<set name="handler" val="ItemSkills" />
		<skills>
			<skill id="27132" level="1" /> <!-- +7 Apocalypse Dual Sword Pack -->
		</skills>
	</item>
	<item id="26010" name="+8 Apocalypse Dual Sword Pack" type="EtcItem">
		<!-- Double-click to obtain the item as described in the pack name. -->
		<set name="icon" val="icon.etc_treasure_box_i08" />
		<set name="is_sellable" val="false" />
		<set name="is_stackable" val="true" />
		<set name="default_action" val="CAPSULE" />
		<set name="material" val="PAPER" />
		<set name="handler" val="ItemSkills" />
		<skills>
			<skill id="27133" level="1" /> <!-- +8 Apocalypse Dual Sword Pack -->
		</skills>
	</item>
	<item id="26011" name="+9 Apocalypse Dual Sword Pack" type="EtcItem">
		<!-- Double-click to obtain the item as described in the pack name. -->
		<set name="icon" val="icon.etc_treasure_box_i08" />
		<set name="is_sellable" val="false" />
		<set name="is_stackable" val="true" />
		<set name="default_action" val="CAPSULE" />
		<set name="material" val="PAPER" />
		<set name="handler" val="ItemSkills" />
		<skills>
			<skill id="27134" level="1" /> <!-- +9 Apocalypse Dual Sword Pack -->
		</skills>
	</item>
	<item id="26012" name="+10 Apocalypse Dual Sword Pack" type="EtcItem">
		<!-- Double-click to obtain the item as described in the pack name. -->
		<set name="icon" val="icon.etc_treasure_box_i08" />
		<set name="is_sellable" val="false" />
		<set name="is_stackable" val="true" />
		<set name="default_action" val="CAPSULE" />
		<set name="material" val="PAPER" />
		<set name="handler" val="ItemSkills" />
		<skills>
			<skill id="27135" level="1" /> <!-- +10 Apocalypse Dual Sword Pack -->
		</skills>
	</item>
	<item id="26013" name="+4 Apocalypse Dual Dagger Pack" type="EtcItem">
		<!-- Double-click to obtain the item as described in the pack name. -->
		<set name="icon" val="icon.etc_treasure_box_i08" />
		<set name="is_sellable" val="false" />
		<set name="is_stackable" val="true" />
		<set name="default_action" val="CAPSULE" />
		<set name="material" val="PAPER" />
		<set name="handler" val="ItemSkills" />
		<skills>
			<skill id="27136" level="1" /> <!-- +4 Apocalypse Dual Dagger Pack -->
		</skills>
	</item>
	<item id="26014" name="+5 Apocalypse Dual Dagger Pack" type="EtcItem">
		<!-- Double-click to obtain the item as described in the pack name. -->
		<set name="icon" val="icon.etc_treasure_box_i08" />
		<set name="is_sellable" val="false" />
		<set name="is_stackable" val="true" />
		<set name="default_action" val="CAPSULE" />
		<set name="material" val="PAPER" />
		<set name="handler" val="ItemSkills" />
		<skills>
			<skill id="27137" level="1" /> <!-- +5 Apocalypse Dual Dagger Pack -->
		</skills>
	</item>
	<item id="26015" name="+6 Apocalypse Dual Dagger Pack" type="EtcItem">
		<!-- Double-click to obtain the item as described in the pack name. -->
		<set name="icon" val="icon.etc_treasure_box_i08" />
		<set name="is_sellable" val="false" />
		<set name="is_stackable" val="true" />
		<set name="default_action" val="CAPSULE" />
		<set name="material" val="PAPER" />
		<set name="handler" val="ItemSkills" />
		<skills>
			<skill id="27138" level="1" /> <!-- +6 Apocalypse Dual Dagger Pack -->
		</skills>
	</item>
	<item id="26016" name="+7 Apocalypse Dual Dagger Pack" type="EtcItem">
		<!-- Double-click to obtain the item as described in the pack name. -->
		<set name="icon" val="icon.etc_treasure_box_i08" />
		<set name="is_sellable" val="false" />
		<set name="is_stackable" val="true" />
		<set name="default_action" val="CAPSULE" />
		<set name="material" val="PAPER" />
		<set name="handler" val="ItemSkills" />
		<skills>
			<skill id="27139" level="1" /> <!-- +7 Apocalypse Dual Dagger Pack -->
		</skills>
	</item>
	<item id="26017" name="+8 Apocalypse Dual Dagger Pack" type="EtcItem">
		<!-- Double-click to obtain the item as described in the pack name. -->
		<set name="icon" val="icon.etc_treasure_box_i08" />
		<set name="is_sellable" val="false" />
		<set name="is_stackable" val="true" />
		<set name="default_action" val="CAPSULE" />
		<set name="material" val="PAPER" />
		<set name="handler" val="ItemSkills" />
		<skills>
			<skill id="27140" level="1" /> <!-- +8 Apocalypse Dual Dagger Pack -->
		</skills>
	</item>
	<item id="26018" name="+9 Apocalypse Dual Daggers Pack" type="EtcItem">
		<!-- Double-click to obtain the item as described in the pack name. -->
		<set name="icon" val="icon.etc_treasure_box_i08" />
		<set name="is_sellable" val="false" />
		<set name="is_stackable" val="true" />
		<set name="default_action" val="CAPSULE" />
		<set name="material" val="PAPER" />
		<set name="handler" val="ItemSkills" />
		<skills>
			<skill id="27141" level="1" /> <!-- +9 Apocalypse Dual Daggers Pack -->
		</skills>
	</item>
	<item id="26019" name="+10 Apocalypse Dual Dagger Pack" type="EtcItem">
		<!-- Double-click to obtain the item as described in the pack name. -->
		<set name="icon" val="icon.etc_treasure_box_i08" />
		<set name="is_sellable" val="false" />
		<set name="is_stackable" val="true" />
		<set name="default_action" val="CAPSULE" />
		<set name="material" val="PAPER" />
		<set name="handler" val="ItemSkills" />
		<skills>
			<skill id="27142" level="1" /> <!-- +10 Apocalypse Dual Dagger Pack -->
		</skills>
	</item>
	<item id="26020" name="+4 Apocalypse Dual Blunt Weapon Pack" type="EtcItem">
		<!-- Double-click to obtain the item as described in the pack name. -->
		<set name="icon" val="icon.etc_treasure_box_i08" />
		<set name="is_sellable" val="false" />
		<set name="is_stackable" val="true" />
		<set name="default_action" val="CAPSULE" />
		<set name="material" val="PAPER" />
		<set name="handler" val="ItemSkills" />
		<skills>
			<skill id="27143" level="1" /> <!-- +4 Apocalypse Dual Blunt Weapon Pack -->
		</skills>
	</item>
	<item id="26021" name="+5 Apocalypse Dual Blunt Weapon Pack" type="EtcItem">
		<!-- Double-click to obtain the item as described in the pack name. -->
		<set name="icon" val="icon.etc_treasure_box_i08" />
		<set name="is_sellable" val="false" />
		<set name="is_stackable" val="true" />
		<set name="default_action" val="CAPSULE" />
		<set name="material" val="PAPER" />
		<set name="handler" val="ItemSkills" />
		<skills>
			<skill id="27144" level="1" /> <!-- +5 Apocalypse Dual Blunt Weapon Pack -->
		</skills>
	</item>
	<item id="26022" name="+6 Apocalypse Dual Blunt Weapon Pack" type="EtcItem">
		<!-- Double-click to obtain the item as described in the pack name. -->
		<set name="icon" val="icon.etc_treasure_box_i08" />
		<set name="is_sellable" val="false" />
		<set name="is_stackable" val="true" />
		<set name="default_action" val="CAPSULE" />
		<set name="material" val="PAPER" />
		<set name="handler" val="ItemSkills" />
		<skills>
			<skill id="27145" level="1" /> <!-- +6 Apocalypse Dual Blunt Weapon Pack -->
		</skills>
	</item>
	<item id="26023" name="+7 Apocalypse Dual Blunt Weapon Pack" type="EtcItem">
		<!-- Double-click to obtain the item as described in the pack name. -->
		<set name="icon" val="icon.etc_treasure_box_i08" />
		<set name="is_sellable" val="false" />
		<set name="is_stackable" val="true" />
		<set name="default_action" val="CAPSULE" />
		<set name="material" val="PAPER" />
		<set name="handler" val="ItemSkills" />
		<skills>
			<skill id="27146" level="1" /> <!-- +7 Apocalypse Dual Blunt Weapon Pack -->
		</skills>
	</item>
	<item id="26024" name="+8 Apocalypse Dual Blunt Weapon Pack" type="EtcItem">
		<!-- Double-click to obtain the item as described in the pack name. -->
		<set name="icon" val="icon.etc_treasure_box_i08" />
		<set name="is_sellable" val="false" />
		<set name="is_stackable" val="true" />
		<set name="default_action" val="CAPSULE" />
		<set name="material" val="PAPER" />
		<set name="handler" val="ItemSkills" />
		<skills>
			<skill id="27147" level="1" /> <!-- +8 Apocalypse Dual Blunt Weapon Pack -->
		</skills>
	</item>
	<item id="26025" name="+9 Apocalypse Dual Blunt Weapon Pack" type="EtcItem">
		<!-- Double-click to obtain the item as described in the pack name. -->
		<set name="icon" val="icon.etc_treasure_box_i08" />
		<set name="is_sellable" val="false" />
		<set name="is_stackable" val="true" />
		<set name="default_action" val="CAPSULE" />
		<set name="material" val="PAPER" />
		<set name="handler" val="ItemSkills" />
		<skills>
			<skill id="27148" level="1" /> <!-- +9 Apocalypse Dual Blunt Weapon Pack -->
		</skills>
	</item>
	<item id="26026" name="+10 Apocalypse Dual Blunt Weapon Pack" type="EtcItem">
		<!-- Double-click to obtain the item as described in the pack name. -->
		<set name="icon" val="icon.etc_treasure_box_i08" />
		<set name="is_sellable" val="false" />
		<set name="is_stackable" val="true" />
		<set name="default_action" val="CAPSULE" />
		<set name="material" val="PAPER" />
		<set name="handler" val="ItemSkills" />
		<skills>
			<skill id="27149" level="1" /> <!-- +10 Apocalypse Dual Blunt Weapon Pack -->
		</skills>
	</item>
	<item id="26027" name="+4 Blessed Requiem Shaper Pack" type="EtcItem">
		<!-- Double-click to obtain the item as described in the pack name. -->
		<set name="icon" val="icon.etc_treasure_box_i08" />
		<set name="is_sellable" val="false" />
		<set name="is_stackable" val="true" />
		<set name="default_action" val="CAPSULE" />
		<set name="material" val="PAPER" />
		<set name="handler" val="ItemSkills" />
		<skills>
			<skill id="27150" level="1" /> <!-- +4 Blessed Requiem Shaper Pack -->
		</skills>
	</item>
	<item id="26028" name="+5 Blessed Requiem Shaper Pack" type="EtcItem">
		<!-- Double-click to obtain the item as described in the pack name. -->
		<set name="icon" val="icon.etc_treasure_box_i08" />
		<set name="is_sellable" val="false" />
		<set name="is_stackable" val="true" />
		<set name="default_action" val="CAPSULE" />
		<set name="material" val="PAPER" />
		<set name="handler" val="ItemSkills" />
		<skills>
			<skill id="27151" level="1" /> <!-- +5 Blessed Requiem Shaper Pack -->
		</skills>
	</item>
	<item id="26029" name="+6 Blessed Requiem Shaper Pack" type="EtcItem">
		<!-- Double-click to obtain the item as described in the pack name. -->
		<set name="icon" val="icon.etc_treasure_box_i08" />
		<set name="is_sellable" val="false" />
		<set name="is_stackable" val="true" />
		<set name="default_action" val="CAPSULE" />
		<set name="material" val="PAPER" />
		<set name="handler" val="ItemSkills" />
		<skills>
			<skill id="27152" level="1" /> <!-- +6 Blessed Requiem Shaper Pack -->
		</skills>
	</item>
	<item id="26030" name="+7 Blessed Requiem Shaper Pack" type="EtcItem">
		<!-- Double-click to obtain the item as described in the pack name. -->
		<set name="icon" val="icon.etc_treasure_box_i08" />
		<set name="is_sellable" val="false" />
		<set name="is_stackable" val="true" />
		<set name="default_action" val="CAPSULE" />
		<set name="material" val="PAPER" />
		<set name="handler" val="ItemSkills" />
		<skills>
			<skill id="27153" level="1" /> <!-- +7 Blessed Requiem Shaper Pack -->
		</skills>
	</item>
	<item id="26031" name="+8 Blessed Requiem Shaper Pack" type="EtcItem">
		<!-- Double-click to obtain the item as described in the pack name. -->
		<set name="icon" val="icon.etc_treasure_box_i08" />
		<set name="is_sellable" val="false" />
		<set name="is_stackable" val="true" />
		<set name="default_action" val="CAPSULE" />
		<set name="material" val="PAPER" />
		<set name="handler" val="ItemSkills" />
		<skills>
			<skill id="27154" level="1" /> <!-- +8 Blessed Requiem Shaper Pack -->
		</skills>
	</item>
	<item id="26032" name="+9 Blessed Requiem Shaper Pack" type="EtcItem">
		<!-- Double-click to obtain the item as described in the pack name. -->
		<set name="icon" val="icon.etc_treasure_box_i08" />
		<set name="is_sellable" val="false" />
		<set name="is_stackable" val="true" />
		<set name="default_action" val="CAPSULE" />
		<set name="material" val="PAPER" />
		<set name="handler" val="ItemSkills" />
		<skills>
			<skill id="27155" level="1" /> <!-- +9 Blessed Requiem Shaper Pack -->
		</skills>
	</item>
	<item id="26033" name="+10 Blessed Requiem Shaper Pack" type="EtcItem">
		<!-- Double-click to obtain the item as described in the pack name. -->
		<set name="icon" val="icon.etc_treasure_box_i08" />
		<set name="is_sellable" val="false" />
		<set name="is_stackable" val="true" />
		<set name="default_action" val="CAPSULE" />
		<set name="material" val="PAPER" />
		<set name="handler" val="ItemSkills" />
		<skills>
			<skill id="27156" level="1" /> <!-- +10 Blessed Requiem Shaper Pack -->
		</skills>
	</item>
	<item id="26034" name="+4 Blessed Requiem Cutter Pack" type="EtcItem">
		<!-- Double-click to obtain the item as described in the pack name. -->
		<set name="icon" val="icon.etc_treasure_box_i08" />
		<set name="is_sellable" val="false" />
		<set name="is_stackable" val="true" />
		<set name="default_action" val="CAPSULE" />
		<set name="material" val="PAPER" />
		<set name="handler" val="ItemSkills" />
		<skills>
			<skill id="27157" level="1" /> <!-- +4 Blessed Requiem Cutter Pack -->
		</skills>
	</item>
	<item id="26035" name="+5 Blessed Requiem Cutter Pack" type="EtcItem">
		<!-- Double-click to obtain the item as described in the pack name. -->
		<set name="icon" val="icon.etc_treasure_box_i08" />
		<set name="is_sellable" val="false" />
		<set name="is_stackable" val="true" />
		<set name="default_action" val="CAPSULE" />
		<set name="material" val="PAPER" />
		<set name="handler" val="ItemSkills" />
		<skills>
			<skill id="27158" level="1" /> <!-- +5 Blessed Requiem Cutter Pack -->
		</skills>
	</item>
	<item id="26036" name="+6 Blessed Requiem Cutter Pack" type="EtcItem">
		<!-- Double-click to obtain the item as described in the pack name. -->
		<set name="icon" val="icon.etc_treasure_box_i08" />
		<set name="is_sellable" val="false" />
		<set name="is_stackable" val="true" />
		<set name="default_action" val="CAPSULE" />
		<set name="material" val="PAPER" />
		<set name="handler" val="ItemSkills" />
		<skills>
			<skill id="27159" level="1" /> <!-- +6 Blessed Requiem Cutter Pack -->
		</skills>
	</item>
	<item id="26037" name="+7 Blessed Requiem Cutter Pack" type="EtcItem">
		<!-- Double-click to obtain the item as described in the pack name. -->
		<set name="icon" val="icon.etc_treasure_box_i08" />
		<set name="is_sellable" val="false" />
		<set name="is_stackable" val="true" />
		<set name="default_action" val="CAPSULE" />
		<set name="material" val="PAPER" />
		<set name="handler" val="ItemSkills" />
		<skills>
			<skill id="27160" level="1" /> <!-- +7 Blessed Requiem Cutter Pack -->
		</skills>
	</item>
	<item id="26038" name="+8 Blessed Requiem Cutter Pack" type="EtcItem">
		<!-- Double-click to obtain the item as described in the pack name. -->
		<set name="icon" val="icon.etc_treasure_box_i08" />
		<set name="is_sellable" val="false" />
		<set name="is_stackable" val="true" />
		<set name="default_action" val="CAPSULE" />
		<set name="material" val="PAPER" />
		<set name="handler" val="ItemSkills" />
		<skills>
			<skill id="27161" level="1" /> <!-- +8 Blessed Requiem Cutter Pack -->
		</skills>
	</item>
	<item id="26039" name="+9 Blessed Requiem Cutter Pack" type="EtcItem">
		<!-- Double-click to obtain the item as described in the pack name. -->
		<set name="icon" val="icon.etc_treasure_box_i08" />
		<set name="is_sellable" val="false" />
		<set name="is_stackable" val="true" />
		<set name="default_action" val="CAPSULE" />
		<set name="material" val="PAPER" />
		<set name="handler" val="ItemSkills" />
		<skills>
			<skill id="27162" level="1" /> <!-- +9 Blessed Requiem Cutter Pack -->
		</skills>
	</item>
	<item id="26040" name="+10 Blessed Requiem Cutter Pack" type="EtcItem">
		<!-- Double-click to obtain the item as described in the pack name. -->
		<set name="icon" val="icon.etc_treasure_box_i08" />
		<set name="is_sellable" val="false" />
		<set name="is_stackable" val="true" />
		<set name="default_action" val="CAPSULE" />
		<set name="material" val="PAPER" />
		<set name="handler" val="ItemSkills" />
		<skills>
			<skill id="27163" level="1" /> <!-- +10 Blessed Requiem Cutter Pack -->
		</skills>
	</item>
	<item id="26041" name="+4 Blessed Requiem Slasher Pack" type="EtcItem">
		<!-- Double-click to obtain the item as described in the pack name. -->
		<set name="icon" val="icon.etc_treasure_box_i08" />
		<set name="is_sellable" val="false" />
		<set name="is_stackable" val="true" />
		<set name="default_action" val="CAPSULE" />
		<set name="material" val="PAPER" />
		<set name="handler" val="ItemSkills" />
		<skills>
			<skill id="27164" level="1" /> <!-- +4 Blessed Requiem Slasher Pack -->
		</skills>
	</item>
	<item id="26042" name="+5 Blessed Requiem Slasher Pack" type="EtcItem">
		<!-- Double-click to obtain the item as described in the pack name. -->
		<set name="icon" val="icon.etc_treasure_box_i08" />
		<set name="is_sellable" val="false" />
		<set name="is_stackable" val="true" />
		<set name="default_action" val="CAPSULE" />
		<set name="material" val="PAPER" />
		<set name="handler" val="ItemSkills" />
		<skills>
			<skill id="27165" level="1" /> <!-- +5 Blessed Requiem Slasher Pack -->
		</skills>
	</item>
	<item id="26043" name="+6 Blessed Requiem Slasher Pack" type="EtcItem">
		<!-- Double-click to obtain the item as described in the pack name. -->
		<set name="icon" val="icon.etc_treasure_box_i08" />
		<set name="is_sellable" val="false" />
		<set name="is_stackable" val="true" />
		<set name="default_action" val="CAPSULE" />
		<set name="material" val="PAPER" />
		<set name="handler" val="ItemSkills" />
		<skills>
			<skill id="27166" level="1" /> <!-- +6 Blessed Requiem Slasher Pack -->
		</skills>
	</item>
	<item id="26044" name="+7 Blessed Requiem Slasher Pack" type="EtcItem">
		<!-- Double-click to obtain the item as described in the pack name. -->
		<set name="icon" val="icon.etc_treasure_box_i08" />
		<set name="is_sellable" val="false" />
		<set name="is_stackable" val="true" />
		<set name="default_action" val="CAPSULE" />
		<set name="material" val="PAPER" />
		<set name="handler" val="ItemSkills" />
		<skills>
			<skill id="27167" level="1" /> <!-- +7 Blessed Requiem Slasher Pack -->
		</skills>
	</item>
	<item id="26045" name="+8 Blessed Requiem Slasher Pack" type="EtcItem">
		<!-- Double-click to obtain the item as described in the pack name. -->
		<set name="icon" val="icon.etc_treasure_box_i08" />
		<set name="is_sellable" val="false" />
		<set name="is_stackable" val="true" />
		<set name="default_action" val="CAPSULE" />
		<set name="material" val="PAPER" />
		<set name="handler" val="ItemSkills" />
		<skills>
			<skill id="27168" level="1" /> <!-- +8 Blessed Requiem Slasher Pack -->
		</skills>
	</item>
	<item id="26046" name="+9 Blessed Requiem Slasher Pack" type="EtcItem">
		<!-- Double-click to obtain the item as described in the pack name. -->
		<set name="icon" val="icon.etc_treasure_box_i08" />
		<set name="is_sellable" val="false" />
		<set name="is_stackable" val="true" />
		<set name="default_action" val="CAPSULE" />
		<set name="material" val="PAPER" />
		<set name="handler" val="ItemSkills" />
		<skills>
			<skill id="27169" level="1" /> <!-- +9 Blessed Requiem Slasher Pack -->
		</skills>
	</item>
	<item id="26047" name="+10 Blessed Requiem Slasher Pack" type="EtcItem">
		<!-- Double-click to obtain the item as described in the pack name. -->
		<set name="icon" val="icon.etc_treasure_box_i08" />
		<set name="is_sellable" val="false" />
		<set name="is_stackable" val="true" />
		<set name="default_action" val="CAPSULE" />
		<set name="material" val="PAPER" />
		<set name="handler" val="ItemSkills" />
		<skills>
			<skill id="27170" level="1" /> <!-- +10 Blessed Requiem Slasher Pack -->
		</skills>
	</item>
	<item id="26048" name="+4 Blessed Requiem Avenger Pack" type="EtcItem">
		<!-- Double-click to obtain the item as described in the pack name. -->
		<set name="icon" val="icon.etc_treasure_box_i08" />
		<set name="is_sellable" val="false" />
		<set name="is_stackable" val="true" />
		<set name="default_action" val="CAPSULE" />
		<set name="material" val="PAPER" />
		<set name="handler" val="ItemSkills" />
		<skills>
			<skill id="27171" level="1" /> <!-- +4 Blessed Requiem Avenger Pack -->
		</skills>
	</item>
	<item id="26049" name="+5 Blessed Requiem Avenger Pack" type="EtcItem">
		<!-- Double-click to obtain the item as described in the pack name. -->
		<set name="icon" val="icon.etc_treasure_box_i08" />
		<set name="is_sellable" val="false" />
		<set name="is_stackable" val="true" />
		<set name="default_action" val="CAPSULE" />
		<set name="material" val="PAPER" />
		<set name="handler" val="ItemSkills" />
		<skills>
			<skill id="27172" level="1" /> <!-- +5 Blessed Requiem Avenger Pack -->
		</skills>
	</item>
	<item id="26050" name="+6 Blessed Requiem Avenger Pack" type="EtcItem">
		<!-- Double-click to obtain the item as described in the pack name. -->
		<set name="icon" val="icon.etc_treasure_box_i08" />
		<set name="is_sellable" val="false" />
		<set name="is_stackable" val="true" />
		<set name="default_action" val="CAPSULE" />
		<set name="material" val="PAPER" />
		<set name="handler" val="ItemSkills" />
		<skills>
			<skill id="27173" level="1" /> <!-- +6 Blessed Requiem Avenger Pack -->
		</skills>
	</item>
	<item id="26051" name="+7 Blessed Requiem Avenger Pack" type="EtcItem">
		<!-- Double-click to obtain the item as described in the pack name. -->
		<set name="icon" val="icon.etc_treasure_box_i08" />
		<set name="is_sellable" val="false" />
		<set name="is_stackable" val="true" />
		<set name="default_action" val="CAPSULE" />
		<set name="material" val="PAPER" />
		<set name="handler" val="ItemSkills" />
		<skills>
			<skill id="27174" level="1" /> <!-- +7 Blessed Requiem Avenger Pack -->
		</skills>
	</item>
	<item id="26052" name="+8 Blessed Requiem Avenger Pack" type="EtcItem">
		<!-- Double-click to obtain the item as described in the pack name. -->
		<set name="icon" val="icon.etc_treasure_box_i08" />
		<set name="is_sellable" val="false" />
		<set name="is_stackable" val="true" />
		<set name="default_action" val="CAPSULE" />
		<set name="material" val="PAPER" />
		<set name="handler" val="ItemSkills" />
		<skills>
			<skill id="27175" level="1" /> <!-- +8 Blessed Requiem Avenger Pack -->
		</skills>
	</item>
	<item id="26053" name="+9 Blessed Requiem Avenger Pack" type="EtcItem">
		<!-- Double-click to obtain the item as described in the pack name. -->
		<set name="icon" val="icon.etc_treasure_box_i08" />
		<set name="is_sellable" val="false" />
		<set name="is_stackable" val="true" />
		<set name="default_action" val="CAPSULE" />
		<set name="material" val="PAPER" />
		<set name="handler" val="ItemSkills" />
		<skills>
			<skill id="27176" level="1" /> <!-- +9 Blessed Requiem Avenger Pack -->
		</skills>
	</item>
	<item id="26054" name="+10 Blessed Requiem Avenger Pack" type="EtcItem">
		<!-- Double-click to obtain the item as described in the pack name. -->
		<set name="icon" val="icon.etc_treasure_box_i08" />
		<set name="is_sellable" val="false" />
		<set name="is_stackable" val="true" />
		<set name="default_action" val="CAPSULE" />
		<set name="material" val="PAPER" />
		<set name="handler" val="ItemSkills" />
		<skills>
			<skill id="27177" level="1" /> <!-- +10 Blessed Requiem Avenger Pack -->
		</skills>
	</item>
	<item id="26055" name="+4 Blessed Requiem Fighter Pack" type="EtcItem">
		<!-- Double-click to obtain the item as described in the pack name. -->
		<set name="icon" val="icon.etc_treasure_box_i08" />
		<set name="is_sellable" val="false" />
		<set name="is_stackable" val="true" />
		<set name="default_action" val="CAPSULE" />
		<set name="material" val="PAPER" />
		<set name="handler" val="ItemSkills" />
		<skills>
			<skill id="27178" level="1" /> <!-- +4 Blessed Requiem Fighter Pack -->
		</skills>
	</item>
	<item id="26056" name="+5 Blessed Requiem Fighter Pack" type="EtcItem">
		<!-- Double-click to obtain the item as described in the pack name. -->
		<set name="icon" val="icon.etc_treasure_box_i08" />
		<set name="is_sellable" val="false" />
		<set name="is_stackable" val="true" />
		<set name="default_action" val="CAPSULE" />
		<set name="material" val="PAPER" />
		<set name="handler" val="ItemSkills" />
		<skills>
			<skill id="27179" level="1" /> <!-- +5 Blessed Requiem Fighter Pack -->
		</skills>
	</item>
	<item id="26057" name="+6 Blessed Requiem Fighter Pack" type="EtcItem">
		<!-- Double-click to obtain the item as described in the pack name. -->
		<set name="icon" val="icon.etc_treasure_box_i08" />
		<set name="is_sellable" val="false" />
		<set name="is_stackable" val="true" />
		<set name="default_action" val="CAPSULE" />
		<set name="material" val="PAPER" />
		<set name="handler" val="ItemSkills" />
		<skills>
			<skill id="27180" level="1" /> <!-- +6 Blessed Requiem Fighter Pack -->
		</skills>
	</item>
	<item id="26058" name="+7 Blessed Requiem Fighter Pack" type="EtcItem">
		<!-- Double-click to obtain the item as described in the pack name. -->
		<set name="icon" val="icon.etc_treasure_box_i08" />
		<set name="is_sellable" val="false" />
		<set name="is_stackable" val="true" />
		<set name="default_action" val="CAPSULE" />
		<set name="material" val="PAPER" />
		<set name="handler" val="ItemSkills" />
		<skills>
			<skill id="27181" level="1" /> <!-- +7 Blessed Requiem Fighter Pack -->
		</skills>
	</item>
	<item id="26059" name="+8 Blessed Requiem Fighter Pack" type="EtcItem">
		<!-- Double-click to obtain the item as described in the pack name. -->
		<set name="icon" val="icon.etc_treasure_box_i08" />
		<set name="is_sellable" val="false" />
		<set name="is_stackable" val="true" />
		<set name="default_action" val="CAPSULE" />
		<set name="material" val="PAPER" />
		<set name="handler" val="ItemSkills" />
		<skills>
			<skill id="27182" level="1" /> <!-- +8 Blessed Requiem Fighter Pack -->
		</skills>
	</item>
	<item id="26060" name="+9 Blessed Requiem Fighter Pack" type="EtcItem">
		<!-- Double-click to obtain the item as described in the pack name. -->
		<set name="icon" val="icon.etc_treasure_box_i08" />
		<set name="is_sellable" val="false" />
		<set name="is_stackable" val="true" />
		<set name="default_action" val="CAPSULE" />
		<set name="material" val="PAPER" />
		<set name="handler" val="ItemSkills" />
		<skills>
			<skill id="27183" level="1" /> <!-- +9 Blessed Requiem Fighter Pack -->
		</skills>
	</item>
	<item id="26061" name="+10 Blessed Requiem Fighter Pack" type="EtcItem">
		<!-- Double-click to obtain the item as described in the pack name. -->
		<set name="icon" val="icon.etc_treasure_box_i08" />
		<set name="is_sellable" val="false" />
		<set name="is_stackable" val="true" />
		<set name="default_action" val="CAPSULE" />
		<set name="material" val="PAPER" />
		<set name="handler" val="ItemSkills" />
		<skills>
			<skill id="27184" level="1" /> <!-- +10 Blessed Requiem Fighter Pack -->
		</skills>
	</item>
	<item id="26062" name="+4 Blessed Requiem Stormer Pack" type="EtcItem">
		<!-- Double-click to obtain the item as described in the pack name. -->
		<set name="icon" val="icon.etc_treasure_box_i08" />
		<set name="is_sellable" val="false" />
		<set name="is_stackable" val="true" />
		<set name="default_action" val="CAPSULE" />
		<set name="material" val="PAPER" />
		<set name="handler" val="ItemSkills" />
		<skills>
			<skill id="27185" level="1" /> <!-- +4 Blessed Requiem Stormer Pack -->
		</skills>
	</item>
	<item id="26063" name="+5 Blessed Requiem Stormer Pack" type="EtcItem">
		<!-- Double-click to obtain the item as described in the pack name. -->
		<set name="icon" val="icon.etc_treasure_box_i08" />
		<set name="is_sellable" val="false" />
		<set name="is_stackable" val="true" />
		<set name="default_action" val="CAPSULE" />
		<set name="material" val="PAPER" />
		<set name="handler" val="ItemSkills" />
		<skills>
			<skill id="27186" level="1" /> <!-- +5 Blessed Requiem Stormer Pack -->
		</skills>
	</item>
	<item id="26064" name="+6 Blessed Requiem Stormer Pack" type="EtcItem">
		<!-- Double-click to obtain the item as described in the pack name. -->
		<set name="icon" val="icon.etc_treasure_box_i08" />
		<set name="is_sellable" val="false" />
		<set name="is_stackable" val="true" />
		<set name="default_action" val="CAPSULE" />
		<set name="material" val="PAPER" />
		<set name="handler" val="ItemSkills" />
		<skills>
			<skill id="27187" level="1" /> <!-- +6 Blessed Requiem Stormer Pack -->
		</skills>
	</item>
	<item id="26065" name="+7 Blessed Requiem Stormer Pack" type="EtcItem">
		<!-- Double-click to obtain the item as described in the pack name. -->
		<set name="icon" val="icon.etc_treasure_box_i08" />
		<set name="is_sellable" val="false" />
		<set name="is_stackable" val="true" />
		<set name="default_action" val="CAPSULE" />
		<set name="material" val="PAPER" />
		<set name="handler" val="ItemSkills" />
		<skills>
			<skill id="27188" level="1" /> <!-- +7 Blessed Requiem Stormer Pack -->
		</skills>
	</item>
	<item id="26066" name="+8 Blessed Requiem Stormer Pack" type="EtcItem">
		<!-- Double-click to obtain the item as described in the pack name. -->
		<set name="icon" val="icon.etc_treasure_box_i08" />
		<set name="is_sellable" val="false" />
		<set name="is_stackable" val="true" />
		<set name="default_action" val="CAPSULE" />
		<set name="material" val="PAPER" />
		<set name="handler" val="ItemSkills" />
		<skills>
			<skill id="27189" level="1" /> <!-- +8 Blessed Requiem Stormer Pack -->
		</skills>
	</item>
	<item id="26067" name="+9 Blessed Requiem Stormer Pack" type="EtcItem">
		<!-- Double-click to obtain the item as described in the pack name. -->
		<set name="icon" val="icon.etc_treasure_box_i08" />
		<set name="is_sellable" val="false" />
		<set name="is_stackable" val="true" />
		<set name="default_action" val="CAPSULE" />
		<set name="material" val="PAPER" />
		<set name="handler" val="ItemSkills" />
		<skills>
			<skill id="27190" level="1" /> <!-- +9 Blessed Requiem Stormer Pack -->
		</skills>
	</item>
	<item id="26068" name="+10 Blessed Requiem Stormer Pack" type="EtcItem">
		<!-- Double-click to obtain the item as described in the pack name. -->
		<set name="icon" val="icon.etc_treasure_box_i08" />
		<set name="is_sellable" val="false" />
		<set name="is_stackable" val="true" />
		<set name="default_action" val="CAPSULE" />
		<set name="material" val="PAPER" />
		<set name="handler" val="ItemSkills" />
		<skills>
			<skill id="27191" level="1" /> <!-- +10 Blessed Requiem Stormer Pack -->
		</skills>
	</item>
	<item id="26069" name="+4 Blessed Requiem Thrower Pack" type="EtcItem">
		<!-- Double-click to obtain the item as described in the pack name. -->
		<set name="icon" val="icon.etc_treasure_box_i08" />
		<set name="is_sellable" val="false" />
		<set name="is_stackable" val="true" />
		<set name="default_action" val="CAPSULE" />
		<set name="material" val="PAPER" />
		<set name="handler" val="ItemSkills" />
		<skills>
			<skill id="27192" level="1" /> <!-- +4 Blessed Requiem Thrower Pack -->
		</skills>
	</item>
	<item id="26070" name="+5 Blessed Requiem Thrower Pack" type="EtcItem">
		<!-- Double-click to obtain the item as described in the pack name. -->
		<set name="icon" val="icon.etc_treasure_box_i08" />
		<set name="is_sellable" val="false" />
		<set name="is_stackable" val="true" />
		<set name="default_action" val="CAPSULE" />
		<set name="material" val="PAPER" />
		<set name="handler" val="ItemSkills" />
		<skills>
			<skill id="27193" level="1" /> <!-- +5 Blessed Requiem Thrower Pack -->
		</skills>
	</item>
	<item id="26071" name="+6 Blessed Requiem Thrower Pack" type="EtcItem">
		<!-- Double-click to obtain the item as described in the pack name. -->
		<set name="icon" val="icon.etc_treasure_box_i08" />
		<set name="is_sellable" val="false" />
		<set name="is_stackable" val="true" />
		<set name="default_action" val="CAPSULE" />
		<set name="material" val="PAPER" />
		<set name="handler" val="ItemSkills" />
		<skills>
			<skill id="27194" level="1" /> <!-- +6 Blessed Requiem Thrower Pack -->
		</skills>
	</item>
	<item id="26072" name="+7 Blessed Requiem Thrower Pack" type="EtcItem">
		<!-- Double-click to obtain the item as described in the pack name. -->
		<set name="icon" val="icon.etc_treasure_box_i08" />
		<set name="is_sellable" val="false" />
		<set name="is_stackable" val="true" />
		<set name="default_action" val="CAPSULE" />
		<set name="material" val="PAPER" />
		<set name="handler" val="ItemSkills" />
		<skills>
			<skill id="27195" level="1" /> <!-- +7 Blessed Requiem Thrower Pack -->
		</skills>
	</item>
	<item id="26073" name="+8 Blessed Requiem Thrower Pack" type="EtcItem">
		<!-- Double-click to obtain the item as described in the pack name. -->
		<set name="icon" val="icon.etc_treasure_box_i08" />
		<set name="is_sellable" val="false" />
		<set name="is_stackable" val="true" />
		<set name="default_action" val="CAPSULE" />
		<set name="material" val="PAPER" />
		<set name="handler" val="ItemSkills" />
		<skills>
			<skill id="27196" level="1" /> <!-- +8 Blessed Requiem Thrower Pack -->
		</skills>
	</item>
	<item id="26074" name="+9 Blessed Requiem Thrower Pack" type="EtcItem">
		<!-- Double-click to obtain the item as described in the pack name. -->
		<set name="icon" val="icon.etc_treasure_box_i08" />
		<set name="is_sellable" val="false" />
		<set name="is_stackable" val="true" />
		<set name="default_action" val="CAPSULE" />
		<set name="material" val="PAPER" />
		<set name="handler" val="ItemSkills" />
		<skills>
			<skill id="27197" level="1" /> <!-- +9 Blessed Requiem Thrower Pack -->
		</skills>
	</item>
	<item id="26075" name="+10 Blessed Requiem Thrower Pack" type="EtcItem">
		<!-- Double-click to obtain the item as described in the pack name. -->
		<set name="icon" val="icon.etc_treasure_box_i08" />
		<set name="is_sellable" val="false" />
		<set name="is_stackable" val="true" />
		<set name="default_action" val="CAPSULE" />
		<set name="material" val="PAPER" />
		<set name="handler" val="ItemSkills" />
		<skills>
			<skill id="27198" level="1" /> <!-- +10 Blessed Requiem Thrower Pack -->
		</skills>
	</item>
	<item id="26076" name="+4 Blessed Requiem Guardian Pack" type="EtcItem">
		<!-- Double-click to obtain the item as described in the pack name. -->
		<set name="icon" val="icon.etc_treasure_box_i08" />
		<set name="is_sellable" val="false" />
		<set name="is_stackable" val="true" />
		<set name="default_action" val="CAPSULE" />
		<set name="material" val="PAPER" />
		<set name="handler" val="ItemSkills" />
		<skills>
			<skill id="27199" level="1" /> <!-- +4 Blessed Requiem Guardian Pack -->
		</skills>
	</item>
	<item id="26077" name="+5 Blessed Requiem Guardian Pack" type="EtcItem">
		<!-- Double-click to obtain the item as described in the pack name. -->
		<set name="icon" val="icon.etc_treasure_box_i08" />
		<set name="is_sellable" val="false" />
		<set name="is_stackable" val="true" />
		<set name="default_action" val="CAPSULE" />
		<set name="material" val="PAPER" />
		<set name="handler" val="ItemSkills" />
		<skills>
			<skill id="27200" level="1" /> <!-- +5 Blessed Requiem Guardian Pack -->
		</skills>
	</item>
	<item id="26078" name="+6 Blessed Requiem Guardian Pack" type="EtcItem">
		<!-- Double-click to obtain the item as described in the pack name. -->
		<set name="icon" val="icon.etc_treasure_box_i08" />
		<set name="is_sellable" val="false" />
		<set name="is_stackable" val="true" />
		<set name="default_action" val="CAPSULE" />
		<set name="material" val="PAPER" />
		<set name="handler" val="ItemSkills" />
		<skills>
			<skill id="27201" level="1" /> <!-- +6 Blessed Requiem Guardian Pack -->
		</skills>
	</item>
	<item id="26079" name="+7 Blessed Requiem Guardian Pack" type="EtcItem">
		<!-- Double-click to obtain the item as described in the pack name. -->
		<set name="icon" val="icon.etc_treasure_box_i08" />
		<set name="is_sellable" val="false" />
		<set name="is_stackable" val="true" />
		<set name="default_action" val="CAPSULE" />
		<set name="material" val="PAPER" />
		<set name="handler" val="ItemSkills" />
		<skills>
			<skill id="27202" level="1" /> <!-- +7 Blessed Requiem Guardian Pack -->
		</skills>
	</item>
	<item id="26080" name="+8 Blessed Requiem Guardian Pack" type="EtcItem">
		<!-- Double-click to obtain the item as described in the pack name. -->
		<set name="icon" val="icon.etc_treasure_box_i08" />
		<set name="is_sellable" val="false" />
		<set name="is_stackable" val="true" />
		<set name="default_action" val="CAPSULE" />
		<set name="material" val="PAPER" />
		<set name="handler" val="ItemSkills" />
		<skills>
			<skill id="27203" level="1" /> <!-- +8 Blessed Requiem Guardian Pack -->
		</skills>
	</item>
	<item id="26081" name="+9 Blessed Requiem Guardian Pack" type="EtcItem">
		<!-- Double-click to obtain the item as described in the pack name. -->
		<set name="icon" val="icon.etc_treasure_box_i08" />
		<set name="is_sellable" val="false" />
		<set name="is_stackable" val="true" />
		<set name="default_action" val="CAPSULE" />
		<set name="material" val="PAPER" />
		<set name="handler" val="ItemSkills" />
		<skills>
			<skill id="27204" level="1" /> <!-- +9 Blessed Requiem Guardian Pack -->
		</skills>
	</item>
	<item id="26082" name="+10 Blessed Requiem Guardian Pack" type="EtcItem">
		<!-- Double-click to obtain the item as described in the pack name. -->
		<set name="icon" val="icon.etc_treasure_box_i08" />
		<set name="is_sellable" val="false" />
		<set name="is_stackable" val="true" />
		<set name="default_action" val="CAPSULE" />
		<set name="material" val="PAPER" />
		<set name="handler" val="ItemSkills" />
		<skills>
			<skill id="27205" level="1" /> <!-- +10 Blessed Requiem Guardian Pack -->
		</skills>
	</item>
	<item id="26083" name="+4 Blessed Requiem Buster Pack" type="EtcItem">
		<!-- Double-click to obtain the item as described in the pack name. -->
		<set name="icon" val="icon.etc_treasure_box_i08" />
		<set name="is_sellable" val="false" />
		<set name="is_stackable" val="true" />
		<set name="default_action" val="CAPSULE" />
		<set name="material" val="PAPER" />
		<set name="handler" val="ItemSkills" />
		<skills>
			<skill id="27206" level="1" /> <!-- +4 Blessed Requiem Buster Pack -->
		</skills>
	</item>
	<item id="26084" name="+5 Blessed Requiem Buster Pack" type="EtcItem">
		<!-- Double-click to obtain the item as described in the pack name. -->
		<set name="icon" val="icon.etc_treasure_box_i08" />
		<set name="is_sellable" val="false" />
		<set name="is_stackable" val="true" />
		<set name="default_action" val="CAPSULE" />
		<set name="material" val="PAPER" />
		<set name="handler" val="ItemSkills" />
		<skills>
			<skill id="27207" level="1" /> <!-- +5 Blessed Requiem Buster Pack -->
		</skills>
	</item>
	<item id="26085" name="+6 Blessed Requiem Buster Pack" type="EtcItem">
		<!-- Double-click to obtain the item as described in the pack name. -->
		<set name="icon" val="icon.etc_treasure_box_i08" />
		<set name="is_sellable" val="false" />
		<set name="is_stackable" val="true" />
		<set name="default_action" val="CAPSULE" />
		<set name="material" val="PAPER" />
		<set name="handler" val="ItemSkills" />
		<skills>
			<skill id="27208" level="1" /> <!-- +6 Blessed Requiem Buster Pack -->
		</skills>
	</item>
	<item id="26086" name="+7 Blessed Requiem Buster Pack" type="EtcItem">
		<!-- Double-click to obtain the item as described in the pack name. -->
		<set name="icon" val="icon.etc_treasure_box_i08" />
		<set name="is_sellable" val="false" />
		<set name="is_stackable" val="true" />
		<set name="default_action" val="CAPSULE" />
		<set name="material" val="PAPER" />
		<set name="handler" val="ItemSkills" />
		<skills>
			<skill id="27209" level="1" /> <!-- +7 Blessed Requiem Buster Pack -->
		</skills>
	</item>
	<item id="26087" name="+8 Blessed Requiem Buster Pack" type="EtcItem">
		<!-- Double-click to obtain the item as described in the pack name. -->
		<set name="icon" val="icon.etc_treasure_box_i08" />
		<set name="is_sellable" val="false" />
		<set name="is_stackable" val="true" />
		<set name="default_action" val="CAPSULE" />
		<set name="material" val="PAPER" />
		<set name="handler" val="ItemSkills" />
		<skills>
			<skill id="27210" level="1" /> <!-- +8 Blessed Requiem Buster Pack -->
		</skills>
	</item>
	<item id="26088" name="+9 Blessed Requiem Buster Pack" type="EtcItem">
		<!-- Double-click to obtain the item as described in the pack name. -->
		<set name="icon" val="icon.etc_treasure_box_i08" />
		<set name="is_sellable" val="false" />
		<set name="is_stackable" val="true" />
		<set name="default_action" val="CAPSULE" />
		<set name="material" val="PAPER" />
		<set name="handler" val="ItemSkills" />
		<skills>
			<skill id="27211" level="1" /> <!-- +9 Blessed Requiem Buster Pack -->
		</skills>
	</item>
	<item id="26089" name="+10 Blessed Requiem Buster Pack" type="EtcItem">
		<!-- Double-click to obtain the item as described in the pack name. -->
		<set name="icon" val="icon.etc_treasure_box_i08" />
		<set name="is_sellable" val="false" />
		<set name="is_stackable" val="true" />
		<set name="default_action" val="CAPSULE" />
		<set name="material" val="PAPER" />
		<set name="handler" val="ItemSkills" />
		<skills>
			<skill id="27212" level="1" /> <!-- +10 Blessed Requiem Buster Pack -->
		</skills>
	</item>
	<item id="26090" name="+4 Blessed Requiem Caster Pack" type="EtcItem">
		<!-- Double-click to obtain the item as described in the pack name. -->
		<set name="icon" val="icon.etc_treasure_box_i08" />
		<set name="is_sellable" val="false" />
		<set name="is_stackable" val="true" />
		<set name="default_action" val="CAPSULE" />
		<set name="material" val="PAPER" />
		<set name="handler" val="ItemSkills" />
		<skills>
			<skill id="27213" level="1" /> <!-- +4 Blessed Requiem Caster Pack -->
		</skills>
	</item>
	<item id="26091" name="+5 Blessed Requiem Caster Pack" type="EtcItem">
		<!-- Double-click to obtain the item as described in the pack name. -->
		<set name="icon" val="icon.etc_treasure_box_i08" />
		<set name="is_sellable" val="false" />
		<set name="is_stackable" val="true" />
		<set name="default_action" val="CAPSULE" />
		<set name="material" val="PAPER" />
		<set name="handler" val="ItemSkills" />
		<skills>
			<skill id="27214" level="1" /> <!-- +5 Blessed Requiem Caster Pack -->
		</skills>
	</item>
	<item id="26092" name="+6 Blessed Requiem Caster Pack" type="EtcItem">
		<!-- Double-click to obtain the item as described in the pack name. -->
		<set name="icon" val="icon.etc_treasure_box_i08" />
		<set name="is_sellable" val="false" />
		<set name="is_stackable" val="true" />
		<set name="default_action" val="CAPSULE" />
		<set name="material" val="PAPER" />
		<set name="handler" val="ItemSkills" />
		<skills>
			<skill id="27215" level="1" /> <!-- +6 Blessed Requiem Caster Pack -->
		</skills>
	</item>
	<item id="26093" name="+7 Blessed Requiem Caster Pack" type="EtcItem">
		<!-- Double-click to obtain the item as described in the pack name. -->
		<set name="icon" val="icon.etc_treasure_box_i08" />
		<set name="is_sellable" val="false" />
		<set name="is_stackable" val="true" />
		<set name="default_action" val="CAPSULE" />
		<set name="material" val="PAPER" />
		<set name="handler" val="ItemSkills" />
		<skills>
			<skill id="27216" level="1" /> <!-- +7 Blessed Requiem Caster Pack -->
		</skills>
	</item>
	<item id="26094" name="+8 Blessed Requiem Caster Pack" type="EtcItem">
		<!-- Double-click to obtain the item as described in the pack name. -->
		<set name="icon" val="icon.etc_treasure_box_i08" />
		<set name="is_sellable" val="false" />
		<set name="is_stackable" val="true" />
		<set name="default_action" val="CAPSULE" />
		<set name="material" val="PAPER" />
		<set name="handler" val="ItemSkills" />
		<skills>
			<skill id="27217" level="1" /> <!-- +8 Blessed Requiem Caster Pack -->
		</skills>
	</item>
	<item id="26095" name="+9 Blessed Requiem Caster Pack" type="EtcItem">
		<!-- Double-click to obtain the item as described in the pack name. -->
		<set name="icon" val="icon.etc_treasure_box_i08" />
		<set name="is_sellable" val="false" />
		<set name="is_stackable" val="true" />
		<set name="default_action" val="CAPSULE" />
		<set name="material" val="PAPER" />
		<set name="handler" val="ItemSkills" />
		<skills>
			<skill id="27218" level="1" /> <!-- +9 Blessed Requiem Caster Pack -->
		</skills>
	</item>
	<item id="26096" name="+10 Blessed Requiem Caster Pack" type="EtcItem">
		<!-- Double-click to obtain the item as described in the pack name. -->
		<set name="icon" val="icon.etc_treasure_box_i08" />
		<set name="is_sellable" val="false" />
		<set name="is_stackable" val="true" />
		<set name="default_action" val="CAPSULE" />
		<set name="material" val="PAPER" />
		<set name="handler" val="ItemSkills" />
		<skills>
			<skill id="27219" level="1" /> <!-- +10 Blessed Requiem Caster Pack -->
		</skills>
	</item>
	<item id="26097" name="+4 Blessed Requiem Retributer Pack" type="EtcItem">
		<!-- Double-click to obtain the item as described in the pack name. -->
		<set name="icon" val="icon.etc_treasure_box_i08" />
		<set name="is_sellable" val="false" />
		<set name="is_stackable" val="true" />
		<set name="default_action" val="CAPSULE" />
		<set name="material" val="PAPER" />
		<set name="handler" val="ItemSkills" />
		<skills>
			<skill id="27220" level="1" /> <!-- +4 Blessed Requiem Retributer Pack -->
		</skills>
	</item>
	<item id="26098" name="+5 Blessed Requiem Retributer Pack" type="EtcItem">
		<!-- Double-click to obtain the item as described in the pack name. -->
		<set name="icon" val="icon.etc_treasure_box_i08" />
		<set name="is_sellable" val="false" />
		<set name="is_stackable" val="true" />
		<set name="default_action" val="CAPSULE" />
		<set name="material" val="PAPER" />
		<set name="handler" val="ItemSkills" />
		<skills>
			<skill id="27221" level="1" /> <!-- +5 Blessed Requiem Retributer Pack -->
		</skills>
	</item>
	<item id="26099" name="+6 Blessed Requiem Retributer Pack" type="EtcItem">
		<!-- Double-click to obtain the item as described in the pack name. -->
		<set name="icon" val="icon.etc_treasure_box_i08" />
		<set name="is_sellable" val="false" />
		<set name="is_stackable" val="true" />
		<set name="default_action" val="CAPSULE" />
		<set name="material" val="PAPER" />
		<set name="handler" val="ItemSkills" />
		<skills>
			<skill id="27222" level="1" /> <!-- +6 Blessed Requiem Retributer Pack -->
		</skills>
	</item>
</list>
